rds2py-0.8.1.dist-info/WHEEL
rds2py-0.8.1.dist-info/top_level.txt
rds2py-0.8.1.dist-info/METADATA
rds2py-0.8.1.dist-info/RECORD
rds2py-0.8.1.dist-info/licenses/LICENSE.txt
rds2py/rdsutils.py
rds2py/read_matrix.py
rds2py/read_se.py
rds2py/read_mae.py
rds2py/read_delayed_matrix.py
rds2py/read_sce.py
rds2py/read_rle.py
rds2py/generics.py
rds2py/lib_rds_parser.cpython-311-x86_64-linux-musl.so
rds2py/read_atomic.py
rds2py/read_granges.py
rds2py/read_compressed_list.py
rds2py/read_factor.py
rds2py/PyRdsReader.py
rds2py/read_frame.py
rds2py/read_dict.py
rds2py/__init__.py
rds2py.libs/libstdc++-0d31ccbe.so.6.0.32
rds2py.libs/libgcc_s-a0b57c20.so.1
