Metadata-Version: 2.4
Name: rds2py
Version: 0.8.1
Summary: Parse and construct Python representations for datasets stored in RDS files
Home-page: https://github.com/biocpy/rds2py
Author: jkanche
Author-email: jayaram.kancherla@gmail.com
License: MIT
Project-URL: Documentation, https://biocpy.github.io/rds2py/
Project-URL: Source, https://github.com/biocpy/rds2py
Platform: Mac
Platform: Linux
Classifier: Development Status :: 4 - Beta
Classifier: Programming Language :: Python
Requires-Python: >=3.9
License-File: LICENSE.txt
Requires-Dist: importlib-metadata; python_version < "3.8"
Requires-Dist: numpy
Requires-Dist: biocutils>=0.1.5
Provides-Extra: optional
Requires-Dist: pandas; extra == "optional"
Requires-Dist: hdf5array; extra == "optional"
Requires-Dist: scipy; extra == "optional"
Requires-Dist: biocframe; extra == "optional"
Requires-Dist: genomicranges>=0.8.4; extra == "optional"
Requires-Dist: summarizedexperiment>=0.6.5; extra == "optional"
Requires-Dist: singlecellexperiment>=0.6.2; extra == "optional"
Requires-Dist: multiassayexperiment>=0.6.0; extra == "optional"
Requires-Dist: compressed_lists>=0.4.4; extra == "optional"
Requires-Dist: biocutils>=0.3.4; extra == "optional"
Provides-Extra: testing
Requires-Dist: setuptools; extra == "testing"
Requires-Dist: pytest; extra == "testing"
Requires-Dist: pytest-cov; extra == "testing"
Requires-Dist: pandas; extra == "testing"
Requires-Dist: hdf5array; extra == "testing"
Requires-Dist: scipy; extra == "testing"
Requires-Dist: biocframe; extra == "testing"
Requires-Dist: genomicranges>=0.8.4; extra == "testing"
Requires-Dist: summarizedexperiment>=0.6.5; extra == "testing"
Requires-Dist: singlecellexperiment>=0.6.2; extra == "testing"
Requires-Dist: multiassayexperiment>=0.6.0; extra == "testing"
Requires-Dist: compressed_lists>=0.4.4; extra == "testing"
Requires-Dist: biocutils>=0.3.4; extra == "testing"
Dynamic: license-file
